raglib/__init__.py
raglib/chunking/__init__.py
raglib/chunking/smart_chunker.py
raglib/embeddings/__init__.py
raglib/embeddings/gemini.py
raglib/embeddings/huggingface.py
raglib/vector_stores/__init__.py
raglib/vector_stores/faiss_store.py
raglib/vector_stores/qdrant_store.py
raglab_easygenius-0.1.0.dist-info/METADATA
raglab_easygenius-0.1.0.dist-info/WHEEL
raglab_easygenius-0.1.0.dist-info/entry_points.txt
raglab_easygenius-0.1.0.dist-info/top_level.txt
raglab_easygenius-0.1.0.dist-info/RECORD
